{
  "tool_name": "mr-fix-my-project-please",
  "tool_version": "3.0.0",
  "integration_type": "quality_analysis_system",
  "deployment_timestamp": "2025-10-13T20:31:38.847795",
  "project_status": {
    "current_phase": "Code Quality Enhancement",
    "phase_status": "COMPLETED",
    "validation_score": 80.0,
    "completion_date": "2025-10-13T20:00:00Z"
  },
  "capabilities": {
    "project_analysis": true,
    "quality_monitoring": true,
    "performance_profiling": true,
    "automated_refactoring": true,
    "dependency_injection": true,
    "type_safety_enhancement": true
  },
  "api_endpoints": {
    "analyze_project": "/api/v1/analyze",
    "quality_check": "/api/v1/quality/check",
    "performance_monitor": "/api/v1/performance/monitor",
    "refactor_suggestions": "/api/v1/refactor/suggest"
  },
  "configuration": {
    "supported_languages": [
      "python"
    ],
    "project_types": [
      "all"
    ],
    "analysis_depth": "comprehensive",
    "quality_standards": "enterprise_grade"
  },
  "transformation_metrics": {
    "original_state": "14,619-line monolithic script with basic functionality",
    "current_state": "Enterprise-grade modular system with comprehensive quality automation",
    "total_phases_completed": 3,
    "phases_completed": [
      "Phase 1: Infrastructure Extraction",
      "Phase 2: Architectural Refactoring with Dependency Injection",
      "Phase 3: Code Quality Enhancement"
    ],
    "total_lines_added": 4900,
    "architectural_improvements": [
      "Enhanced type safety with runtime validation",
      "Comprehensive static analysis pipeline",
      "Automated quality gates and pre-commit hooks",
      "Advanced performance profiling and monitoring",
      "Intelligent refactoring and optimization tools",
      "Quality system setup automation"
    ]
  },
  "next_phase_readiness": {
    "phase_4_status": "READY",
    "phase_name": "Documentation Completion",
    "readiness_score": 85,
    "blocking_issues": [],
    "recommended_next_steps": [
      "Create comprehensive API documentation",
      "Generate architecture decision records",
      "Create developer onboarding guides",
      "Implement example-based tutorials"
    ],
    "estimated_duration": "2 weeks",
    "complexity_level": "Medium"
  }
}